kokoro_onnx/__init__.py
kokoro_onnx/config.json
kokoro_onnx/config.py
kokoro_onnx/log.py
kokoro_onnx/py.typed
kokoro_onnx/tokenizer.py
kokoro_onnx/trim.py
kokoro_onnx-0.4.8.dist-info/METADATA
kokoro_onnx-0.4.8.dist-info/WHEEL
kokoro_onnx-0.4.8.dist-info/licenses/LICENSE
kokoro_onnx-0.4.8.dist-info/RECORD
