Metadata-Version: 2.4
Name: kokoro-onnx
Version: 0.4.8
Summary: TTS with kokoro and onnx runtime
Project-URL: Homepage, https://github.com/thewh1teagle/kokoro-onnx
Project-URL: Repository, https://github.com/thewh1teagle/kokoro-onnx
Project-URL: Issues, https://github.com/thewh1teagle/kokoro-onnx/issues
Author-email: thewh1teagle <61390950+thewh1teagle@users.noreply.github.com>
License-File: LICENSE
Requires-Python: <3.14,>=3.10
Requires-Dist: colorlog>=6.9.0
Requires-Dist: espeakng-loader>=0.2.4
Requires-Dist: numpy>=2.0.2
Requires-Dist: onnxruntime>=1.20.1
Requires-Dist: phonemizer-fork==3.3.1
Provides-Extra: gpu
Requires-Dist: onnxruntime-gpu>=1.20.1; (platform_machine == 'x86_64' and sys_platform != 'darwin') and extra == 'gpu'
